alibabacloud/__init__.py
alibabacloud/client.py
alibabacloud/compat.py
alibabacloud/exceptions.py
alibabacloud/request.py
alibabacloud/session.py
alibabacloud/clients/__init__.py
alibabacloud/clients/aas_20150701.py
alibabacloud/clients/actiontrail_20171204.py
alibabacloud/clients/aegis_20161111.py
alibabacloud/clients/afs_20180112.py
alibabacloud/clients/alidns_20150109.py
alibabacloud/clients/alimt_20190107.py
alibabacloud/clients/arms4finance_20171130.py
alibabacloud/clients/arms_20190808.py
alibabacloud/clients/batchcompute_20150630.py
alibabacloud/clients/bss_20140714.py
alibabacloud/clients/bssopenapi_20171214.py
alibabacloud/clients/cas_20180813.py
alibabacloud/clients/cbn_20170912.py
alibabacloud/clients/ccc_20170705.py
alibabacloud/clients/ccs_20171001.py
alibabacloud/clients/cdn_20141111.py
alibabacloud/clients/cdn_20180510.py
alibabacloud/clients/cloudmarketing_20180910.py
alibabacloud/clients/cloudphoto_20170711.py
alibabacloud/clients/cloudwf_20170328.py
alibabacloud/clients/cms_20190101.py
alibabacloud/clients/companyreg_20190508.py
alibabacloud/clients/crm_20150408.py
alibabacloud/clients/cspro_20181217.py
alibabacloud/clients/cusanalytic_sc_online_20190524.py
alibabacloud/clients/dbs_20190306.py
alibabacloud/clients/dcdn_20180115.py
alibabacloud/clients/dds_20151201.py
alibabacloud/clients/dms_enterprise_20181101.py
alibabacloud/clients/drds_20190123.py
alibabacloud/clients/dts_20180801.py
alibabacloud/clients/dybaseapi_20170525.py
alibabacloud/clients/dypnsapi_20170525.py
alibabacloud/clients/dyvmsapi_20170525.py
alibabacloud/clients/ecs_20140526.py
alibabacloud/clients/edas_20170801.py
alibabacloud/clients/ehpc_20180412.py
alibabacloud/clients/emr_20160408.py
alibabacloud/clients/ens_20171110.py
alibabacloud/clients/ess_20140828.py
alibabacloud/clients/faas_20170824.py
alibabacloud/clients/ft_20180713.py
alibabacloud/clients/gpdb_20160503.py
alibabacloud/clients/green_20180509.py
alibabacloud/clients/hbr_20170908.py
alibaba_cloud_python_sdk_v2-1.0.5.dist-info/LICENSE
alibaba_cloud_python_sdk_v2-1.0.5.dist-info/METADATA
alibaba_cloud_python_sdk_v2-1.0.5.dist-info/WHEEL
alibaba_cloud_python_sdk_v2-1.0.5.dist-info/top_level.txt
alibaba_cloud_python_sdk_v2-1.0.5.dist-info/RECORD
