Metadata-Version: 2.1
Name: alibaba-cloud-python-sdk-v2
Version: 1.0.5
Summary: Alibaba Cloud Python SDK 2.0
Home-page: https://github.com/aliyun/alibabacloud-python-sdk-v2
Author: Alibaba Cloud
Author-email: alibaba-cloud-sdk-dev-team@list.alibaba-inc.com
License: Apache License 2.0
Platform: UNKNOWN
Classifier: Development Status :: 1 - Planning
Classifier: Intended Audience :: Developers
Classifier: Natural Language :: English
Classifier: License :: OSI Approved :: Apache Software License
Classifier: Programming Language :: Python
Classifier: Programming Language :: Python :: 2.7
Classifier: Programming Language :: Python :: 3
Classifier: Programming Language :: Python :: 3.3
Classifier: Programming Language :: Python :: 3.4
Classifier: Programming Language :: Python :: 3.5
Classifier: Programming Language :: Python :: 3.6
Classifier: Programming Language :: Python :: 3.7
Requires-Dist: jmespath (<1.0.0,>=0.9.3)
Requires-Dist: mock (>=2.0.0)
